SemanticVersion.py
semtag.py
semtag-0.2.1.dist-info/licenses/LICENSE
semtag-0.2.1.dist-info/METADATA
semtag-0.2.1.dist-info/WHEEL
semtag-0.2.1.dist-info/entry_points.txt
semtag-0.2.1.dist-info/top_level.txt
semtag-0.2.1.dist-info/RECORD
