Metadata-Version: 2.4
Name: semtag
Version: 0.2.1
Summary: A tool for managing semantic version tags in git repositories
Author-email: Mateusz Mikrut <mateusz.mikrut@gmail.com>
License-Expression: MIT
Project-URL: Homepage, https://github.com/mateuszmikrut/semtag
Project-URL: Bug Reports, https://github.com/mateuszmikrut/semtag/issues
Project-URL: Source, https://github.com/mateuszmikrut/semtag
Keywords: git,tags,semantic-versioning,semver,version-control
Classifier: Development Status :: 4 - Beta
Classifier: Intended Audience :: Developers
Classifier: Topic :: Software Development :: Version Control :: Git
Classifier: Programming Language :: Python :: 3
Classifier: Programming Language :: Python :: 3.8
Classifier: Programming Language :: Python :: 3.9
Classifier: Programming Language :: Python :: 3.10
Classifier: Programming Language :: Python :: 3.11
Classifier: Programming Language :: Python :: 3.12
Requires-Python: >=3.8
License-File: LICENSE
Requires-Dist: gitpython>=3.1.0
Dynamic: license-file
